edan/__init__.py
edan-0.5.1.dist-info/METADATA
edan-0.5.1.dist-info/WHEEL
edan-0.5.1.dist-info/licenses/LICENSE
edan-0.5.1.dist-info/RECORD
