Metadata-Version: 2.3
Name: edan
Version: 0.5.1
Summary: Python module to query the Smithsonian's internal Enterprise Digital Asset Network (EDAN).
Project-URL: Homepage, https://github.com/smithsonian/edan-python
Project-URL: Bug Tracker, https://github.com/smithsonian/edan-python/issues
Author-email: "Luis J. Villanueva" <villanueval@si.edu>
License-File: LICENSE
Classifier: License :: OSI Approved :: Apache Software License
Classifier: Operating System :: OS Independent
Classifier: Programming Language :: Python :: 3
Requires-Python: >=3.11
